odoo/addons/stock_picking_import_serial_number/README.rst
odoo/addons/stock_picking_import_serial_number/__init__.py
odoo/addons/stock_picking_import_serial_number/__manifest__.py
odoo/addons/stock_picking_import_serial_number/i18n/es.po
odoo/addons/stock_picking_import_serial_number/i18n/it.po
odoo/addons/stock_picking_import_serial_number/i18n/stock_picking_import_serial_number.pot
odoo/addons/stock_picking_import_serial_number/i18n/tr.po
odoo/addons/stock_picking_import_serial_number/models/__init__.py
odoo/addons/stock_picking_import_serial_number/models/res_config_settings.py
odoo/addons/stock_picking_import_serial_number/readme/CONFIGURE.md
odoo/addons/stock_picking_import_serial_number/readme/CONTRIBUTORS.md
odoo/addons/stock_picking_import_serial_number/readme/DESCRIPTION.md
odoo/addons/stock_picking_import_serial_number/readme/USAGE.md
odoo/addons/stock_picking_import_serial_number/security/ir.model.access.csv
odoo/addons/stock_picking_import_serial_number/static/description/icon.png
odoo/addons/stock_picking_import_serial_number/static/description/index.html
odoo/addons/stock_picking_import_serial_number/tests/__init__.py
odoo/addons/stock_picking_import_serial_number/tests/common.py
odoo/addons/stock_picking_import_serial_number/tests/test_stock_picking_import_serial_number.py
odoo/addons/stock_picking_import_serial_number/tests/data/SNImport-1.xls
odoo/addons/stock_picking_import_serial_number/tests/data/SNImport-2.xls
odoo/addons/stock_picking_import_serial_number/views/res_config_settings_views.xml
odoo/addons/stock_picking_import_serial_number/views/stock_picking.xml
odoo/addons/stock_picking_import_serial_number/wizard/__init__.py
odoo/addons/stock_picking_import_serial_number/wizard/import_serial_number_view.xml
odoo/addons/stock_picking_import_serial_number/wizard/import_serial_number_wizard.py
odoo_addon_stock_picking_import_serial_number-18.0.1.0.0.2.dist-info/METADATA
odoo_addon_stock_picking_import_serial_number-18.0.1.0.0.2.dist-info/WHEEL
odoo_addon_stock_picking_import_serial_number-18.0.1.0.0.2.dist-info/top_level.txt
odoo_addon_stock_picking_import_serial_number-18.0.1.0.0.2.dist-info/RECORD
